test_pypi/__init__.py
test_pypi_uploads/__init__.py
test_pypi_uploads-0.1.0rc5.dist-info/METADATA
test_pypi_uploads-0.1.0rc5.dist-info/WHEEL
test_pypi_uploads-0.1.0rc5.dist-info/top_level.txt
test_pypi_uploads-0.1.0rc5.dist-info/RECORD
