Metadata-Version: 2.1
Name: test-pypi-uploads
Version: 0.1.0rc5
Summary: Package for testing PyPi uploads.
Author: angrybayblade
License: MIT
Classifier: Operating System :: MacOS
Classifier: Operating System :: Microsoft
Classifier: Operating System :: Unix
Classifier: Programming Language :: Python :: 3.7
Classifier: Programming Language :: Python :: 3.8
Classifier: Programming Language :: Python :: 3.9
Classifier: Programming Language :: Python :: 3.10
Requires-Python: >=3.8
